modular_backtest/__init__.py
modular_backtest/engine.py
modular_backtest/result.py
modular_backtest/types.py
modular_backtest/backends/__init__.py
modular_backtest/backends/allocation.py
modular_backtest/backends/api.py
modular_backtest/backends/asset.py
modular_backtest/backends/commission.py
modular_backtest/backends/execution.py
modular_backtest/backends/order.py
modular_backtest/backends/signal.py
modular_backtest/backends/slippage.py
modular_backtest/data/__init__.py
modular_backtest/data/utils.py
modular_backtest/data/bundles/__init__.py
modular_backtest/data/bundles/yahoo.py
modular_backtest/factors/__init__.py
modular_backtest/factors/adx.py
modular_backtest/factors/adx.pyi
modular_backtest/factors/atr.py
modular_backtest/factors/atr.pyi
modular_backtest/factors/bbands.py
modular_backtest/factors/bbands.pyi
modular_backtest/factors/ema.py
modular_backtest/factors/ema.pyi
modular_backtest/factors/handler.py
modular_backtest/factors/rsi.py
modular_backtest/factors/rsi.pyi
modular_backtest/factors/sma.py
modular_backtest/factors/sma.pyi
modular_backtest/models/__init__.py
modular_backtest/models/abstract.py
modular_backtest/models/handler.py
modular_backtest/models/asset_selection/__init__.py
modular_backtest/models/asset_selection/manual.py
modular_backtest/models/order_execution/__init__.py
modular_backtest/models/order_execution/instant.py
modular_backtest/models/portfolio_construction/__init__.py
modular_backtest/models/portfolio_construction/equal.py
modular_backtest/models/risk_management/__init__.py
modular_backtest/models/risk_management/void.py
modular_backtest/models/signal_generation/__init__.py
modular_backtest/models/signal_generation/static.py
modular_backtest-0.0.1.post2.dist-info/LICENSE
modular_backtest-0.0.1.post2.dist-info/METADATA
modular_backtest-0.0.1.post2.dist-info/WHEEL
modular_backtest-0.0.1.post2.dist-info/top_level.txt
modular_backtest-0.0.1.post2.dist-info/RECORD
