Metadata-Version: 2.1
Name: modular-backtest
Version: 0.0.1.post2
Summary: Backtesting Framework for Algorithmic Trading
Author: Kachain Fuangsung
Author-email: kachain.f@outlook.com
License: MIT License
Project-URL: Homepage, https://github.com/kfuangsung/modular-backtest
Project-URL: Documentation, https://kfuangsung.github.io/modular-backtest
Project-URL: Repository, https://github.com/kfuangsung/modular-backtest
Project-URL: Changelog, https://github.com/kfuangsung/modular-backtest/blob/main/CHANGELOG.md
Classifier: Programming Language :: Python :: 3
Requires-Python: >=3.12
License-File: LICENSE
Requires-Dist: numpy<3,>=2
Requires-Dist: pandas<3,>=2
Requires-Dist: zipline-reloaded>=3.1
Requires-Dist: pydantic<3,>=2
Requires-Dist: multimethod<3,>=2
Requires-Dist: ta-lib>=0.5
Requires-Dist: bottleneck>=1.4
Requires-Dist: more-itertools<11,>=10
Requires-Dist: tqdm<5,>=4
Requires-Dist: yfinance>=0.2.50
Requires-Dist: tradingview-screener>=2.5
Provides-Extra: docs
Requires-Dist: sphinx-autoapi; extra == "docs"
Requires-Dist: pydata-sphinx-theme; extra == "docs"
